api_ninja/__init__.py
api_ninja/cli.py
api_ninja/color.py
api_ninja/core.py
api_ninja/memory_store.py
api_ninja/models.py
api_ninja/plugin.py
api_ninja/agents/__init__.py
api_ninja/agents/flow_generator.py
api_ninja/agents/planner.py
api_ninja/agents/request_generator.py
api_ninja/agents/result_evaluation.py
api_test_ninja-1.0.10.dist-info/METADATA
api_test_ninja-1.0.10.dist-info/WHEEL
api_test_ninja-1.0.10.dist-info/entry_points.txt
api_test_ninja-1.0.10.dist-info/licenses/LICENSE
api_test_ninja-1.0.10.dist-info/RECORD
