Metadata-Version: 2.4
Name: api-test-ninja
Version: 1.0.10
Summary: API Testing Framework to automate and simplify API testing using LLM Agents and tests defined in plain English.
Project-URL: Homepage, https://github.com/ssilwal29/api-ninja
Project-URL: Documentation, https://ssilwal29.github.io/api-ninja
Project-URL: Repository, https://github.com/ssilwal29/api-ninja
Project-URL: Bug Tracker, https://github.com/ssilwal29/api-ninja/issues
Project-URL: Changelog, https://github.com/ssilwal29/api-ninja/blob/main/CHANGELOG.md
Author-email: Sajan Silwal <silwalsajan@gmail.com>
Maintainer-email: Sajan Silwal <silwalsajan@gmail.com>
License: MIT
License-File: LICENSE
Keywords: api validation,api-testing,integration testing,llm testing,openai api testing,openapi testing,pytest api testing,rest api testing,test api,test automation,testing,testing-framework
Classifier: Development Status :: 4 - Beta
Classifier: Framework :: Pytest
Classifier: Intended Audience :: Developers
Classifier: License :: OSI Approved :: MIT License
Classifier: Programming Language :: Python :: 3
Classifier: Topic :: Software Development :: Testing
Classifier: Topic :: Utilities
Requires-Python: >=3.11
Requires-Dist: openai-agents>=0.0.14
Requires-Dist: openai>=1.76.0
Requires-Dist: pydantic>=2.11.4
Requires-Dist: pytest-md-report>=0.7.0
Requires-Dist: pytest-sugar>=1.0.0
Requires-Dist: pytest-xdist>=3.6.1
Requires-Dist: pytest>=8.3.5
Requires-Dist: pyyaml>=6.0.2
Requires-Dist: ragas>=0.2.15
Requires-Dist: requests>=2.32.3
Requires-Dist: rich>=14.0.0
